aind_labtracks_service_async_client/__init__.py
aind_labtracks_service_async_client/api_client.py
aind_labtracks_service_async_client/api_response.py
aind_labtracks_service_async_client/configuration.py
aind_labtracks_service_async_client/exceptions.py
aind_labtracks_service_async_client/py.typed
aind_labtracks_service_async_client/rest.py
aind_labtracks_service_async_client/api/__init__.py
aind_labtracks_service_async_client/api/default_api.py
aind_labtracks_service_async_client/api/healthcheck_api.py
aind_labtracks_service_async_client/models/__init__.py
aind_labtracks_service_async_client/models/health_check.py
aind_labtracks_service_async_client/models/http_validation_error.py
aind_labtracks_service_async_client/models/mouse_custom_class.py
aind_labtracks_service_async_client/models/subject.py
aind_labtracks_service_async_client/models/task.py
aind_labtracks_service_async_client/models/validation_error.py
aind_labtracks_service_async_client/models/validation_error_loc_inner.py
aind_labtracks_service_async_client-0.3.0.dist-info/METADATA
aind_labtracks_service_async_client-0.3.0.dist-info/WHEEL
aind_labtracks_service_async_client-0.3.0.dist-info/top_level.txt
aind_labtracks_service_async_client-0.3.0.dist-info/RECORD
